sugaro/__init__.py
sugaro/files.py
sugaro/mathx.py
sugaro/net.py
sugaro/utils.py
sugaro-0.1.0.dist-info/licenses/LICENSE
sugaro-0.1.0.dist-info/METADATA
sugaro-0.1.0.dist-info/WHEEL
sugaro-0.1.0.dist-info/top_level.txt
sugaro-0.1.0.dist-info/RECORD
