Metadata-Version: 2.4
Name: sugaro
Version: 0.1.0
Summary: A lightweight multi-purpose Python toolkit with zero dependencies.
Author: Your Name
Author-email: you@example.com
License: MIT
Keywords: utils,toolkit,sugar,short,no-dependency
Classifier: Programming Language :: Python :: 3
Classifier: License :: OSI Approved :: MIT License
Classifier: Operating System :: OS Independent
Requires-Python: >=3.7
License-File: LICENSE
Dynamic: license-file
